vidclip/__init__.py
vidclip/vidclip.py
vidclip-0.2.0.dist-info/LICENSE
vidclip-0.2.0.dist-info/METADATA
vidclip-0.2.0.dist-info/WHEEL
vidclip-0.2.0.dist-info/entry_points.txt
vidclip-0.2.0.dist-info/top_level.txt
vidclip-0.2.0.dist-info/RECORD
