Metadata-Version: 2.1
Name: vidclip
Version: 0.2.0
Summary: Trim and merge videos using TOML
Author: makes
Project-URL: Homepage, https://github.com/makes/vidclip
Project-URL: Bug Tracker, https://github.com/makes/vidclip/issues
Requires-Python: >=3.9
License-File: LICENSE
Requires-Dist: toml
Requires-Dist: typer
